Metadata-Version: 2.1
Name: Dino-AI
Version: 1.0
Summary: A simple ai that automates the dino game on chrome.
Author: Akmal Riyas
License-File: Licenses.txt
